{
   "asset" : {
      "generator" : "osg2cesiumApp",
      "version" : "1.0"
   },
   "root" : {
      "boundingVolume" : {
         "box" : [
            -60.242385864257812,
            -26.715625762939453,
            107.34135437011719,
            2.7580089569091797,
            0.0,
            0.0,
            0.0,
            2.1124973297119141,
            0.0,
            0.0,
            0.0,
            1.061248779296875
         ]
      },
      "children" : [
         {
            "boundingVolume" : {
               "box" : [
                  -60.24609375,
                  -26.715625762939453,
                  107.33812713623047,
                  2.75390625,
                  0.0,
                  0.0,
                  0.0,
                  2.1046857833862305,
                  0.0,
                  0.0,
                  0.0,
                  1.059112548828125
               ]
            },
            "content" : {
               "uri" : "Tile_+000_+000_L24_0002000.json"
            },
            "geometricError" : 0.022290093824267387
         }
      ],
      "content" : {
         "uri" : "Tile_+000_+000_L23_000200.b3dm"
      },
      "geometricError" : 0.044580187648534775
   }
}
