{
   "asset" : {
      "generator" : "osg2cesiumApp",
      "version" : "1.0"
   },
   "root" : {
      "boundingVolume" : {
         "box" : [
            -49.25,
            -18.328125,
            106.62295532226562,
            2.7656211853027344,
            0.0,
            0.0,
            0.0,
            2.1124973297119141,
            0.0,
            0.0,
            0.0,
            0.075435638427734375
         ]
      },
      "children" : [
         {
            "boundingVolume" : {
               "box" : [
                  -49.25,
                  -18.328125,
                  106.62324523925781,
                  2.7578125,
                  0.0,
                  0.0,
                  0.0,
                  2.1046867370605469,
                  0.0,
                  0.0,
                  0.0,
                  0.072467803955078125
               ]
            },
            "content" : {
               "uri" : "Tile_+000_+000_L24_0030000.json"
            },
            "geometricError" : 0.021358819678425789
         }
      ],
      "content" : {
         "uri" : "Tile_+000_+000_L23_003000.b3dm"
      },
      "geometricError" : 0.042717639356851578
   }
}
