{
   "asset" : {
      "generator" : "osg2cesiumApp",
      "version" : "1.0"
   },
   "root" : {
      "boundingVolume" : {
         "box" : [
            -15.755012512207031,
            12.756250381469727,
            122.54332733154297,
            1.012824535369873,
            0.0,
            0.0,
            0.0,
            1.1015610694885254,
            0.0,
            0.0,
            0.0,
            0.252960205078125
         ]
      },
      "children" : [
         {
            "boundingVolume" : {
               "box" : [
                  -15.755012512207031,
                  12.756250381469727,
                  122.543701171875,
                  1.008918285369873,
                  0.0,
                  0.0,
                  0.0,
                  1.0976557731628418,
                  0.0,
                  0.0,
                  0.0,
                  0.25259017944335938
               ]
            },
            "content" : {
               "uri" : "Tile_+001_+001_L25_00141300.json"
            },
            "geometricError" : 0.0046560713090002537
         }
      ],
      "content" : {
         "uri" : "Tile_+001_+001_L24_0014130.b3dm"
      },
      "geometricError" : 0.0093121426180005074
   }
}
