{
   "asset" : {
      "generator" : "osg2cesiumApp",
      "version" : "1.0"
   },
   "root" : {
      "boundingVolume" : {
         "box" : [
            -22.240116119384766,
            12.756250381469727,
            120.25288391113281,
            0.23104763031005859,
            0.0,
            0.0,
            0.0,
            1.1015610694885254,
            0.0,
            0.0,
            0.0,
            0.96600341796875
         ]
      },
      "content" : {
         "uri" : "Tile_+001_+001_L24_0014540.b3dm"
      },
      "geometricError" : 0.0088449139147996902
   }
}
