{
   "asset" : {
      "generator" : "osg2cesiumApp",
      "version" : "1.0"
   },
   "root" : {
      "boundingVolume" : {
         "box" : [
            25.141059875488281,
            28.626197814941406,
            123.57859802246094,
            0.76943111419677734,
            0.0,
            0.0,
            0.0,
            0.80589008331298828,
            0.0,
            0.0,
            0.0,
            1.0255966186523438
         ]
      },
      "children" : [
         {
            "boundingVolume" : {
               "box" : [
                  25.141059875488281,
                  28.627651214599609,
                  123.57980346679688,
                  0.76552486419677734,
                  0.0,
                  0.0,
                  0.0,
                  0.80343914031982422,
                  0.0,
                  0.0,
                  0.0,
                  1.0228919982910156
               ]
            },
            "content" : {
               "uri" : "Tile_+002_+001_L25_00356400.json"
            },
            "geometricError" : 0.0046460465528070927
         }
      ],
      "content" : {
         "uri" : "Tile_+002_+001_L24_0035640.b3dm"
      },
      "geometricError" : 0.0092920931056141853
   }
}
