{
   "asset" : {
      "generator" : "osg2cesiumApp",
      "version" : "1.0"
   },
   "root" : {
      "boundingVolume" : {
         "box" : [
            18.0625,
            11.662500381469727,
            121.97633361816406,
            2.203122615814209,
            0.0,
            0.0,
            0.0,
            2.203122615814209,
            0.0,
            0.0,
            0.0,
            0.48590469360351562
         ]
      },
      "children" : [
         {
            "boundingVolume" : {
               "box" : [
                  16.96875,
                  10.568750381469727,
                  121.64228820800781,
                  1.1015610694885254,
                  0.0,
                  0.0,
                  0.0,
                  1.1015610694885254,
                  0.0,
                  0.0,
                  0.0,
                  0.15186691284179688
               ]
            },
            "content" : {
               "uri" : "Tile_+002_+001_L24_0012300.json"
            },
            "geometricError" : 0.0096715856343507767
         },
         {
            "boundingVolume" : {
               "box" : [
                  19.15625,
                  10.568750381469727,
                  121.77458190917969,
                  1.1015605926513672,
                  0.0,
                  0.0,
                  0.0,
                  1.1015610694885254,
                  0.0,
                  0.0,
                  0.0,
                  0.21603012084960938
               ]
            },
            "content" : {
               "uri" : "Tile_+002_+001_L24_0012310.json"
            },
            "geometricError" : 0.0096715856343507767
         },
         {
            "boundingVolume" : {
               "box" : [
                  16.96875,
                  12.756250381469727,
                  122.03156280517578,
                  1.1015610694885254,
                  0.0,
                  0.0,
                  0.0,
                  1.1015610694885254,
                  0.0,
                  0.0,
                  0.0,
                  0.4250335693359375
               ]
            },
            "content" : {
               "uri" : "Tile_+002_+001_L24_0012320.json"
            },
            "geometricError" : 0.0096715856343507767
         },
         {
            "boundingVolume" : {
               "box" : [
                  19.15625,
                  12.756250381469727,
                  121.94522094726562,
                  1.1015605926513672,
                  0.0,
                  0.0,
                  0.0,
                  1.1015610694885254,
                  0.0,
                  0.0,
                  0.0,
                  0.25536346435546875
               ]
            },
            "content" : {
               "uri" : "Tile_+002_+001_L24_0012330.json"
            },
            "geometricError" : 0.0096715856343507767
         }
      ],
      "content" : {
         "uri" : "Tile_+002_+001_L23_001230t3.b3dm"
      },
      "geometricError" : 0.019343171268701553
   }
}
