{
   "asset" : {
      "generator" : "osg2cesiumApp",
      "version" : "1.0"
   },
   "root" : {
      "boundingVolume" : {
         "box" : [
            13.6875,
            7.2875003814697266,
            122.02391052246094,
            2.2031221389770508,
            0.0,
            0.0,
            0.0,
            2.2031223773956299,
            0.0,
            0.0,
            0.0,
            0.59007644653320312
         ]
      },
      "children" : [
         {
            "boundingVolume" : {
               "box" : [
                  13.6875,
                  8.3812503814697266,
                  122.02188110351562,
                  2.1953115463256836,
                  0.0,
                  0.0,
                  0.0,
                  1.1015610694885254,
                  0.0,
                  0.0,
                  0.0,
                  0.58804702758789062
               ]
            },
            "content" : {
               "uri" : "Tile_+002_+001_L24_0012000.json"
            },
            "geometricError" : 0.01556233037263155
         },
         {
            "boundingVolume" : {
               "box" : [
                  12.59375,
                  6.1937499046325684,
                  121.81521606445312,
                  1.1015615463256836,
                  0.0,
                  0.0,
                  0.0,
                  1.1015610694885254,
                  0.0,
                  0.0,
                  0.0,
                  0.33864212036132812
               ]
            },
            "content" : {
               "uri" : "Tile_+002_+001_L24_0012010.json"
            },
            "geometricError" : 0.0097820460796356201
         },
         {
            "boundingVolume" : {
               "box" : [
                  14.78125,
                  6.1937499046325684,
                  121.7095947265625,
                  1.1015615463256836,
                  0.0,
                  0.0,
                  0.0,
                  1.1015610694885254,
                  0.0,
                  0.0,
                  0.0,
                  0.25022506713867188
               ]
            },
            "content" : {
               "uri" : "Tile_+002_+001_L24_0012020.json"
            },
            "geometricError" : 0.0096813300624489784
         }
      ],
      "content" : {
         "uri" : "Tile_+002_+001_L23_001200t2.b3dm"
      },
      "geometricError" : 0.0311246607452631
   }
}
