{
   "asset" : {
      "generator" : "osg2cesiumApp",
      "version" : "1.0"
   },
   "root" : {
      "boundingVolume" : {
         "box" : [
            10.40625,
            12.756250381469727,
            122.59003448486328,
            1.1015615463256836,
            0.0,
            0.0,
            0.0,
            1.1015610694885254,
            0.0,
            0.0,
            0.0,
            0.5118408203125
         ]
      },
      "children" : [
         {
            "boundingVolume" : {
               "box" : [
                  10.40625,
                  12.756250381469727,
                  122.58843994140625,
                  1.0976552963256836,
                  0.0,
                  0.0,
                  0.0,
                  1.0976557731628418,
                  0.0,
                  0.0,
                  0.0,
                  0.51024627685546875
               ]
            },
            "content" : {
               "uri" : "Tile_+002_+001_L25_00033200.json"
            },
            "geometricError" : 0.0050307596102356911
         }
      ],
      "content" : {
         "uri" : "Tile_+002_+001_L24_0003320.b3dm"
      },
      "geometricError" : 0.010061519220471382
   }
}
